nmstools/__init__.py
nmstools/nmstools.py
nmstools-1.0.dist-info/DESCRIPTION.rst
nmstools-1.0.dist-info/METADATA
nmstools-1.0.dist-info/RECORD
nmstools-1.0.dist-info/WHEEL
nmstools-1.0.dist-info/metadata.json
nmstools-1.0.dist-info/top_level.txt
