Metadata-Version: 2.0
Name: nmstools
Version: 1.0
Summary: PyPI Tutorial
Home-page: https://github.com/stjuliet
Author: stjuliet
Author-email: andy19966212@126.com
License: MIT-0
Platform: UNKNOWN
Requires-Python: >=3.5
Requires-Dist: numpy
